mcp_server_svn/__init__.py
mcp_server_svn/__main__.py
mcp_server_svn/mcp_server_svn.py
mcp_server_svn/tools/__init__.py
mcp_server_svn/tools/add.py
mcp_server_svn/tools/checkout.py
mcp_server_svn/tools/cleanup.py
mcp_server_svn/tools/commit.py
mcp_server_svn/tools/create_branch.py
mcp_server_svn/tools/delete_branch.py
mcp_server_svn/tools/diff.py
mcp_server_svn/tools/list_branches.py
mcp_server_svn/tools/log.py
mcp_server_svn/tools/merge.py
mcp_server_svn/tools/resolve.py
mcp_server_svn/tools/revert.py
mcp_server_svn/tools/status.py
mcp_server_svn/tools/switch.py
mcp_server_svn/tools/update.py
mcp_server_svn/tools/version.py
mcp_server_svn/tools/whoami.py
mcp_server_svn-0.1.4.post2.dist-info/METADATA
mcp_server_svn-0.1.4.post2.dist-info/WHEEL
mcp_server_svn-0.1.4.post2.dist-info/entry_points.txt
mcp_server_svn-0.1.4.post2.dist-info/top_level.txt
mcp_server_svn-0.1.4.post2.dist-info/RECORD
