Metadata-Version: 2.4
Name: mcp-server-svn
Version: 0.1.4.post2
Summary: An MCP server integration for SVN
Author-email: Manav Desai <manav27202@gmail.com>
Classifier: Programming Language :: Python :: 3
Classifier: Programming Language :: Python :: 3.10
Classifier: Programming Language :: Python :: 3.11
Classifier: Programming Language :: Python :: 3.12
Requires-Python: >=3.10
Requires-Dist: fastmcp
